README.md
setup.py
ediri_port/__init__.py
ediri_port/_inputs.py
ediri_port/_utilities.py
ediri_port/action.py
ediri_port/blueprint.py
ediri_port/entity.py
ediri_port/outputs.py
ediri_port/provider.py
ediri_port/pulumi-plugin.json
ediri_port/py.typed
ediri_port.egg-info/PKG-INFO
ediri_port.egg-info/SOURCES.txt
ediri_port.egg-info/dependency_links.txt
ediri_port.egg-info/not-zip-safe
ediri_port.egg-info/requires.txt
ediri_port.egg-info/top_level.txt
ediri_port/config/__init__.py
ediri_port/config/vars.py