Metadata-Version: 2.1
Name: ediri-port
Version: 0.8.4
Summary: A Pulumi package for creating and managing Port resources.
Home-page: https://www.pulumi.com
License: Apache-2.0
Project-URL: Repository, https://github.com/dirien/pulumi-port-labs
Keywords: pulumi port category/utility
Platform: UNKNOWN
